{
    "name": "MContractTeam",
    "fields": [
        {
            "fieldName": "status",
            "fieldType": "String"
        },
        {
            "fieldName": "uid",
            "fieldType": "UUID"
        },
        {
            "fieldName": "active",
            "fieldType": "Boolean"
        }
    ],
    "relationships": [
        {
            "relationshipType": "many-to-one",
            "otherEntityName": "aDOrganization",
            "otherEntityRelationshipName": "mContractTeam",
            "relationshipValidateRules": "required",
            "relationshipName": "adOrganization",
            "otherEntityField": "id"
        },
        {
            "relationshipType": "many-to-one",
            "otherEntityName": "mContract",
            "otherEntityRelationshipName": "mContractTeam",
            "relationshipValidateRules": "required",
            "relationshipName": "contract",
            "otherEntityField": "id"
        }
    ],
    "changelogDate": "20210723050300",
    "entityTableName": "m_contract_team",
    "dto": "mapstruct",
    "pagination": "pagination",
    "service": "serviceClass",
    "jpaMetamodelFiltering": true,
    "fluentMethods": true,
    "readOnly": false,
    "embedded": false,
    "clientRootFolder": "",
    "applications": "*",
    "skipClient": true
}